pybart/__init__.py
pybart/api.py
pybart/conllu_wrapper.py
pybart/constraints.py
pybart/converter.py
pybart/graph_token.py
pybart/matcher.py
pybart/spacy_wrapper.py
pybart_nlp-3.2.14.dist-info/LICENSE
pybart_nlp-3.2.14.dist-info/METADATA
pybart_nlp-3.2.14.dist-info/WHEEL
pybart_nlp-3.2.14.dist-info/top_level.txt
pybart_nlp-3.2.14.dist-info/RECORD
