Metadata-Version: 2.1
Name: pybart-nlp
Version: 3.2.14
Summary: python converter from UD-tree to BART-graph representations
Home-page: https://github.com/allenai/pybart
Author: Aryeh Tiktinsky
Author-email: aryehgigi@gmail.com
License: UNKNOWN
Platform: UNKNOWN
Classifier: Programming Language :: Python :: 3.7
Classifier: License :: OSI Approved :: Apache Software License
Classifier: Operating System :: OS Independent
Requires-Python: >=3.7, <3.9
License-File: LICENSE
